{
  "preRequisites:11": [
    11
  ],
  "properties:10": {
    "betterquesting:10": {
      "desc:8": "Angel blocks are used for the quite niche purpose of building when there are no blocks around.\n\nTo use them you place them down forehead.",
      "icon:10": {
        "Count:3": 1,
        "id:8": "extrautils2:angelblock"
      },
      "name:8": "Building in Nothing"
    }
  },
  "questID:3": 27,
  "tasks:9": {
    "0:10": {
      "index:3": 0,
      "requiredItems:9": {
        "0:10": {
          "Count:3": 1,
          "id:8": "extrautils2:angelblock"
        }
      },
      "taskID:8": "bq_standard:retrieval"
    }
  }
}