{
  "preRequisites:11": [
    2
  ],
  "properties:10": {
    "betterquesting:10": {
      "desc:8": "No Description",
      "icon:10": {
        "Count:3": 1,
        "id:8": "minecraft:grass"
      },
      "name:8": "Lore of Earth"
    }
  },
  "questID:3": 47,
  "tasks:9": {
    "0:10": {
      "index:3": 0,
      "requiredItems:9": {
        "0:10": {
          "Count:3": 1,
          "Damage:2": 223,
          "id:8": "ebwizardry:spell_book"
        },
        "1:10": {
          "Count:3": 1,
          "Damage:2": 292,
          "id:8": "ebwizardry:spell_book"
        },
        "2:10": {
          "Count:3": 1,
          "Damage:2": 294,
          "id:8": "ebwizardry:spell_book"
        },
        "3:10": {
          "Count:3": 1,
          "Damage:2": 219,
          "id:8": "ebwizardry:spell_book"
        },
        "4:10": {
          "Count:3": 1,
          "Damage:2": 113,
          "id:8": "ebwizardry:spell_book"
        },
        "5:10": {
          "Count:3": 1,
          "Damage:2": 141,
          "id:8": "ebwizardry:spell_book"
        },
        "6:10": {
          "Count:3": 1,
          "Damage:2": 9,
          "id:8": "ebwizardry:spell_book"
        },
        "7:10": {
          "Count:3": 1,
          "Damage:2": 8,
          "id:8": "ebwizardry:spell_book"
        }
      },
      "taskID:8": "bq_standard:retrieval"
    },
    "1:10": {
      "index:3": 1,
      "requiredItems:9": {
        "0:10": {
          "Count:3": 1,
          "Damage:2": 35,
          "id:8": "ebwizardry:spell_book"
        },
        "1:10": {
          "Count:3": 1,
          "Damage:2": 34,
          "id:8": "ebwizardry:spell_book"
        },
        "2:10": {
          "Count:3": 1,
          "Damage:2": 33,
          "id:8": "ebwizardry:spell_book"
        },
        "3:10": {
          "Count:3": 1,
          "Damage:2": 32,
          "id:8": "ebwizardry:spell_book"
        },
        "4:10": {
          "Count:3": 1,
          "Damage:2": 224,
          "id:8": "ebwizardry:spell_book"
        },
        "5:10": {
          "Count:3": 1,
          "Damage:2": 215,
          "id:8": "ebwizardry:spell_book"
        },
        "6:10": {
          "Count:3": 1,
          "Damage:2": 214,
          "id:8": "ebwizardry:spell_book"
        },
        "7:10": {
          "Count:3": 1,
          "Damage:2": 191,
          "id:8": "ebwizardry:spell_book"
        },
        "8:10": {
          "Count:3": 1,
          "Damage:2": 297,
          "id:8": "ebwizardry:spell_book"
        },
        "9:10": {
          "Count:3": 1,
          "Damage:2": 36,
          "id:8": "ebwizardry:spell_book"
        },
        "10:10": {
          "Count:3": 1,
          "Damage:2": 37,
          "id:8": "ebwizardry:spell_book"
        },
        "11:10": {
          "Count:3": 1,
          "Damage:2": 149,
          "id:8": "ebwizardry:spell_book"
        },
        "12:10": {
          "Count:3": 1,
          "Damage:2": 118,
          "id:8": "ebwizardry:spell_book"
        },
        "13:10": {
          "Count:3": 1,
          "Damage:2": 117,
          "id:8": "ebwizardry:spell_book"
        },
        "14:10": {
          "Count:3": 1,
          "Damage:2": 237,
          "id:8": "tfspellpack:twilight_spell_book"
        },
        "15:10": {
          "Count:3": 1,
          "Damage:2": 238,
          "id:8": "tfspellpack:twilight_spell_book"
        },
        "16:10": {
          "Count:3": 1,
          "Damage:2": 239,
          "id:8": "tfspellpack:twilight_spell_book"
        }
      },
      "taskID:8": "bq_standard:retrieval"
    }
  }
}